earthquakelatest/__init__.py
earthquake_IDN-0.6.dist-info/LICENSE
earthquake_IDN-0.6.dist-info/METADATA
earthquake_IDN-0.6.dist-info/WHEEL
earthquake_IDN-0.6.dist-info/top_level.txt
earthquake_IDN-0.6.dist-info/RECORD
