Metadata-Version: 2.1
Name: earthquake-IDN
Version: 0.6
Summary: This package will scrape data from [BMKG](https://www.bmkg.go.id) to get the latest quake happened in Indonesia
Home-page: https://github.com/student-of-remoteworkerid/latest-indonesia-earthquake
Author: Muhammad Shaufi Imanulhaq
Author-email: imanshaufi14@gmail.com
License: UNKNOWN
Project-URL: Website, https://remoteworker.id
Platform: UNKNOWN
Classifier: Programming Language :: Python :: 3
Classifier: License :: OSI Approved :: GNU General Public License v3 (GPLv3)
Classifier: Operating System :: OS Independent
Classifier: Development Status :: 5 - Production/Stable
Requires-Python: >=3.6
License-File: LICENSE
